KvFront/__init__.py
KvFront/config.py
KvFront/connection.py
KvFront/conninfo.py
KvFront/constants.py
KvFront/kvfront.py
KvFront/main.py
KvFront/memcached.py
KvFront/newmemkey.py
KvFront/newrediskey.py
KvFront/redis_conninfo.py
KvFront/redis_helper.py
KvFront/selected_obj.py
KvFront-2.6.0.data/data/KvFront/config/server.conf
KvFront-2.6.0.data/data/KvFront/ui/addserver.ui
KvFront-2.6.0.data/data/KvFront/ui/detailpage-2.ui
KvFront-2.6.0.data/data/KvFront/ui/detailpage4redis-2.ui
KvFront-2.6.0.data/data/KvFront/ui/main.ui
KvFront-2.6.0.data/data/KvFront/ui/newmemkey.ui
KvFront-2.6.0.data/data/KvFront/ui/newrediskey.ui
KvFront-2.6.0.data/data/share/applications/kvfront.desktop
KvFront-2.6.0.data/data/share/icons/data-man-symbolic.svg
KvFront-2.6.0.data/data/share/icons/flush-symbolic.svg
KvFront-2.6.0.data/data/share/icons/kvfront.png
KvFront-2.6.0.data/data/share/icons/ladd-symbolic.svg
KvFront-2.6.0.data/data/share/icons/ldelete-data-symbolic.svg
KvFront-2.6.0.data/data/share/icons/lexport-symbolic.svg
KvFront-2.6.0.data/data/share/icons/lmenu-symbolic.svg
KvFront-2.6.0.data/data/share/icons/lnewkey-symbolic.svg
KvFront-2.6.0.data/data/share/icons/lremove-symbolic.svg
KvFront-2.6.0.data/data/share/icons/lrun-symbolic.svg
KvFront-2.6.0.data/data/share/icons/lterminal-symbolic.svg
KvFront-2.6.0.data/data/share/icons/refresh-symbolic.svg
KvFront-2.6.0.data/data/share/icons/scan-symbolic.svg
KvFront-2.6.0.data/data/share/icons/status-symbolic.svg
KvFront-2.6.0.dist-info/LICENSE
KvFront-2.6.0.dist-info/METADATA
KvFront-2.6.0.dist-info/WHEEL
KvFront-2.6.0.dist-info/entry_points.txt
KvFront-2.6.0.dist-info/top_level.txt
KvFront-2.6.0.dist-info/RECORD
