Metadata-Version: 1.2
Name: KvFront
Version: 2.6.0
Summary: KvFront is a gui tool for memcached & redis developed by GTK+3
Home-page: https://github.com/wgalaxy/KvFront
Author: Gavin W
Author-email: qmongofront@live.com
License: GPLv3
Keywords: memcached,memcache,memcached GUI,memcached front,redis,redis GUI
Platform: any
Requires-Python: >=3.6
